MANIFEST.in
sc-releaser.cfg
setup.cfg
setup.py
docs/HISTORY.txt
docs/INSTALL.txt
docs/LICENSE.GPL
docs/LICENSE.txt
sc/__init__.py
sc.base.cdn.egg-info/PKG-INFO
sc.base.cdn.egg-info/SOURCES.txt
sc.base.cdn.egg-info/dependency_links.txt
sc.base.cdn.egg-info/entry_points.txt
sc.base.cdn.egg-info/namespace_packages.txt
sc.base.cdn.egg-info/not-zip-safe
sc.base.cdn.egg-info/requires.txt
sc.base.cdn.egg-info/top_level.txt
sc/base/__init__.py
sc/base/cdn/README.txt
sc/base/cdn/__init__.py
sc/base/cdn/configure.zcml
sc/base/cdn/interfaces.py
sc/base/cdn/patch.py
sc/base/cdn/profiles.zcml
sc/base/cdn/tests.py
sc/base/cdn/version.txt
sc/base/cdn/vocabularies.py
sc/base/cdn/controlpanel/__init__.py
sc/base/cdn/controlpanel/cdn.py
sc/base/cdn/controlpanel/configure.zcml
sc/base/cdn/docs/AlternateHostname.txt
sc/base/cdn/docs/Benchmark.txt
sc/base/cdn/docs/CDN.txt
sc/base/cdn/docs/CoralCDN.txt
sc/base/cdn/docs/MultipleHostnames.txt
sc/base/cdn/docs/__init__.py
sc/base/cdn/locales/manual.pot
sc/base/cdn/locales/rebuildPOT.sh
sc/base/cdn/locales/sc.base.cdn.pot
sc/base/cdn/locales/pt_BR/LC_MESSAGES/sc.base.cdn.po
sc/base/cdn/profiles/default/actionicons.xml
sc/base/cdn/profiles/default/controlpanel.xml
sc/base/cdn/profiles/default/metadata.xml
sc/base/cdn/profiles/default/propertiestool.xml
sc/base/cdn/providers/__init__.py
sc/base/cdn/providers/configure.zcml
sc/base/cdn/providers/coralcdn.py
sc/base/cdn/providers/hostname.py
sc/base/cdn/providers/multiplehostnames.py