Metadata-Version: 1.0
Name: sc.base.cdn
Version: 0.6-
Summary: UNKNOWN
Home-page: http://www.simplesconsultoria.com.br/
Author: Simples Consultoria
Author-email: products@simplesconsultoria.com.br
License: UNKNOWN
Keywords: cdn web plone distribution
Platform: UNKNOWN
Classifier: Framework :: Plone
Classifier: Programming Language :: Python
Classifier: Topic :: Software Development :: Libraries :: Python Modules
Classifier: Topic :: Internet :: WWW/HTTP
